LICENSE
MANIFEST.in
README.md
pyproject.toml
setup.cfg
setup.py
wagtail_3display/__init__.py
wagtail_3display/admin.py
wagtail_3display/apps.py
wagtail_3display/blocks.py
wagtail_3display/models.py
wagtail_3display/tests.py
wagtail_3display/views.py
wagtail_3display.egg-info/PKG-INFO
wagtail_3display.egg-info/SOURCES.txt
wagtail_3display.egg-info/dependency_links.txt
wagtail_3display.egg-info/requires.txt
wagtail_3display.egg-info/top_level.txt
wagtail_3display/migrations/__init__.py
wagtail_3display/migrations/__pycache__/__init__.cpython-311.pyc
wagtail_3display/static/wagtail_3display/js/3display.js
wagtail_3display/static/wagtail_3display/js/3display.js.LICENSE.txt
wagtail_3display/templates/wagtail_3display/blocks/threedisplay.html
wagtail_3display/templatetags/__init__.py
wagtail_3display/templatetags/threedisplay_tags.py
wagtail_3display/templatetags/__pycache__/__init__.cpython-311.pyc
wagtail_3display/templatetags/__pycache__/showcase_tags.cpython-311.pyc
wagtail_3display/templatetags/__pycache__/threedisplay_tags.cpython-311.pyc